README.md
setup.py
docker_chaos_monkey/__init__.py
docker_chaos_monkey/command_line.py
docker_chaos_monkey/docker_chaos_monkey.py
docker_chaos_monkey/log_helper.py
docker_chaos_monkey.egg-info/PKG-INFO
docker_chaos_monkey.egg-info/SOURCES.txt
docker_chaos_monkey.egg-info/dependency_links.txt
docker_chaos_monkey.egg-info/entry_points.txt
docker_chaos_monkey.egg-info/not-zip-safe
docker_chaos_monkey.egg-info/requires.txt
docker_chaos_monkey.egg-info/top_level.txt